LICENSE
MANIFEST.in
README.md
setup.py
coinmarketcapapi/__init__.py
coinmarketcapapi/cache.py
coinmarketcapapi/errors.py
coinmarketcapapi/types.py
coinmarketcapapi/utils.py
pyCoinMarketCapAPI.egg-info/PKG-INFO
pyCoinMarketCapAPI.egg-info/SOURCES.txt
pyCoinMarketCapAPI.egg-info/dependency_links.txt
pyCoinMarketCapAPI.egg-info/not-zip-safe
pyCoinMarketCapAPI.egg-info/requires.txt
pyCoinMarketCapAPI.egg-info/top_level.txt
tests/__init__.py
tests/cache_test.py
tests/coins_select_mechanism_test.py
tests/errors_test.py