Metadata-Version: 1.1
Name: pyCoinMarketCapAPI
Version: 0.4
Summary: Python support for coimarketcap's APIs with cache and timezones support.
Home-page: https://github.com/lucaoflaif/pyCoinMarketCapAPI
Author: Luca Di Vita
Author-email: d.v.luca99@gmail.com
License: MIT
Keywords: cryptocurrency bitcoin api market
Platform: UNKNOWN
Classifier: Development Status :: 5 - Production/Stable
Classifier: Intended Audience :: Developers
Classifier: License :: OSI Approved :: MIT License
Classifier: Programming Language :: Python :: 3
Classifier: Topic :: Software Development :: Libraries :: Python Modules
